poclib3/__init__.py
poclib3/atlas/__init__.py
poclib3/atlas/atlas.py
poclib3/brute/__init__.py
poclib3/brute/config.py
poclib3/webshell/__init__.py
poclib3/webshell/utils.py
poclib3/webshell/webshell.py
poclib3/webshell/webshells/behinder3/shell.aspx
poclib3/webshell/webshells/behinder4/default_aes/shell.aspx
poclib3/webshell/webshells/behinder4/default_aes/shell.jsp
poclib3/webshell/webshells/behinder4/default_aes/shell.php
poclib3/webshell/webshells/godzilla/cshap_aes_base64.ashx
poclib3/webshell/webshells/godzilla/cshap_aes_base64.aspx
poclib3/webshell/webshells/godzilla/java_aes_base64.jsp
poclib3/webshell/webshells/godzilla/java_aes_base64.jspx
poclib3/webshell/webshells/godzilla/php_xor_base64.php
poclib3/webshell/webshells/other/define_class_memshell.jsp
poclib3-0.1.2.dist-info/METADATA
poclib3-0.1.2.dist-info/WHEEL
poclib3-0.1.2.dist-info/top_level.txt
poclib3-0.1.2.dist-info/RECORD
