Metadata-Version: 2.1
Name: poclib3
Version: 0.1.2
Summary: A library to generate processed webshell instances
Author: haruka
Author-email: admin@haruka.com
Requires-Dist: requests
